<?xml version="1.0" encoding="UTF-8" ?>
<!DOCTYPE mapper PUBLIC "-//mybatis.org//DTD Mapper 3.0//EN" "http://mybatis.org/dtd/mybatis-3-mapper.dtd" >
<mapper namespace="cn.whaley.moretv.member.mapper.order.OrderMapper" >
    <!--
        This Mapper File generated by MyBatis Generator Extend at 2017-03-31 15:00:02
    -->
    
  <select id="listByAccountId" resultMap="BaseResultMap">
    select 
    <include refid="Base_Column_List" />
    from business_order bod
    where bod.account_id = #{accountId}
    order by bod.create_time desc
  </select>
    
    
  <select id="getByOrderCode" resultMap="BaseResultMap" parameterType="java.lang.String" >
    select 
    <include refid="Base_Column_List" />
    from business_order bod
    where bod.order_code = #{orderCode,jdbcType=VARCHAR}
    	  and bod.valid_status = 1
  </select>
  
  <select id="getByOrderIdForUpdate" resultMap="BaseResultMap" parameterType="java.lang.Integer" >
    select 
    <include refid="Base_Column_List" />
    from business_order bod
    where bod.id = #{orderId,jdbcType=INTEGER}
    	  and bod.valid_status = 1 for update
  </select>

  
  <update id="updateOrderPayStatus" parameterType="java.util.Map" >
    update business_order
    set pay_status = #{newPayStatus,jdbcType=INTEGER},
        update_time = #{updateTime,jdbcType=TIMESTAMP}
    where order_code = #{orderCode,jdbcType=VARCHAR} and pay_status = #{oldPayStatus,jdbcType=INTEGER} and trade_status = #{tradeStatus,jdbcType=INTEGER}
  </update>
</mapper>